tfgraphviz/__init__.py
tfgraphviz/graphviz_style.py
tfgraphviz/graphviz_wrapper.py
tfgraphviz/jupyter_helper.py
tfgraphviz-0.0.8.dist-info/LICENSE
tfgraphviz-0.0.8.dist-info/METADATA
tfgraphviz-0.0.8.dist-info/WHEEL
tfgraphviz-0.0.8.dist-info/top_level.txt
tfgraphviz-0.0.8.dist-info/RECORD
