Metadata-Version: 2.1
Name: tfgraphviz
Version: 0.0.8
Summary: A visualization tool to show a graph like TensorFlow and TensorBoard
Home-page: https://github.com/akimach/tfgraphviz
Author: akimacho
Author-email: kimura.akimasa@gmail.com
License: MIT
Keywords: tensorflow tensor machine-learning graphviz ml deep-learning neural-network
Platform: UNKNOWN
Classifier: Programming Language :: Python :: 2.7
Classifier: Programming Language :: Python :: 3.3
Classifier: License :: OSI Approved :: MIT License
Classifier: Intended Audience :: Science/Research
Classifier: Intended Audience :: Education
Classifier: Topic :: Scientific/Engineering :: Mathematics
Requires-Dist: graphviz
